{"mapSizeX":10,"mapSizeY":9,"wordDatas":[{"x":3,"y":3,"direction":1,"word":"편리미엄","info":"편리함과 프리미엄의 합성어로 데우기만 하면 되는 간편식이나, 가사 노동을 줄여주는 가전제품 등 편리함이 소비 트렌드에 중심이 됐음을 나타내는 말 ","wordType":4},{"x":5,"y":2,"direction":2,"word":"원미동사람들","info":"1980년대 부천시 원미동이라는 동네를 배경으로 하는 소설로 삭막한 현대사회를 살아가는 서민의 이야기를 그렸다. ","wordType":1},{"x":3,"y":5,"direction":1,"word":"조동사","info":"본동사를 도와 그 의미를 더해주는 동사로 보조동사라고도 한다. '먹지 말아라'에서 '말다'에 해당하는 동사 ","wordType":1},{"x":3,"y":5,"direction":2,"word":"조명","info":"연극이나 콘서트 무대에서 어떤 공간을 밝게 비추는 빛","wordType":2},{"x":0,"y":6,"direction":1,"word":"가격혁명","info":"16세기부터 17세기까지 유럽 여러 나라에 신대륙으로부터 금과 은이 대량으로 들어오면서 물가가 2배 이상 상승한 사건","wordType":10},{"x":1,"y":6,"direction":2,"word":"격려금","info":"용기나 의욕이 솟아나고 사기(士氣)를 북돋워 주기 위해 주는 돈","wordType":3},{"x":0,"y":8,"direction":1,"word":"오금","info":"무릎을 구부렸을 때 오목하게 들어간 부분 ","wordType":1},{"x":3,"y":2,"direction":2,"word":"우편","info":"편지나 기타 물품을 조직에 의해 규칙적으로 보내는 업무 ","wordType":3},{"x":0,"y":2,"direction":1,"word":"포정해우","info":"뛰어난 솜씨를 가진 포정이 소를 바른다는 뜻의 사자성어 ","wordType":5},{"x":0,"y":0,"direction":2,"word":"해리포터","info":"조앤 k 롤링이 쓴 판타지 소설로 호그와트 마법 학교에 다는 마법사들의 이야기 ","wordType":6},{"x":0,"y":0,"direction":1,"word":"해먹","info":"기둥 사이나 나무 그늘 같은 곳에 매달아 침대로 쓰는 그물 ","wordType":3},{"x":4,"y":7,"direction":1,"word":"산들바람","info":"시원하고 가볍게 부는 바람","wordType":3},{"x":7,"y":6,"direction":2,"word":"다람쥐","info":"밤, 도토리를 좋아하는 동물로 귀엽게 생긴 생김새 때문에 반려동물로 사람과 같이 살기도 한다.","wordType":3},{"x":7,"y":6,"direction":1,"word":"다보탑","info":"대한민국 10원짜리 동전에서 볼 수 있는 신라시대 탑으로 우리나라를 대표하는 아름답고 정교한 돌탑","wordType":7},{"x":8,"y":4,"direction":2,"word":"대자보","info":"대학가의 벽에 크게 붙여서 정치적인 일이나 학교의 문제 등을 밝히는 벽보 ","wordType":1},{"x":8,"y":4,"direction":1,"word":"대행","info":"남을 대신해서 어떤 권한이나 직무를 행하는 사람 (예) 주차00, 배달00, 구매00","wordType":9},{"x":9,"y":1,"direction":2,"word":"신혼여행","info":"결혼식을 마친 신혼부부가 함께 가는 여행","wordType":3},{"x":8,"y":1,"direction":1,"word":"백신","info":"인간이나 동물의 질병에 대해서 후천적으로 면역을 부여하는 의약품 ","wordType":8},{"x":8,"y":0,"direction":2,"word":"방백","info":"곁에 사람을 두고 혼자 하는 말로 연극 대사의 특수한 독백을 일컫는 말  ","wordType":1}]}