{"mapSizeX":10,"mapSizeY":9,"wordDatas":[{"x":2,"y":3,"direction":1,"word":"그린테리어","info":"식물로 하는 인테리어란 뜻으로 심리적 안정과 실내공기 정화의 효과가 있다. ","wordType":4},{"x":2,"y":3,"direction":2,"word":"그루터기","info":"나무기를 베고 남은 아랫부분 또는 물건의 아랫부분을 비유적으로 이르는 말 (예) 소나무 0000에 앉다, 산 0000","wordType":3},{"x":0,"y":5,"direction":1,"word":"포스터","info":"광고나 선전을 위한 매개체 중 하나로 일정한 내용이 적힌 종이나 상징적인 그림을 길거리나 사람의 눈에 많이 띄는 곳에 붙인다. ","wordType":2},{"x":0,"y":4,"direction":2,"word":"창포물","info":"음력 5월 5일 단오날에는 000에 머리를 감는 풍속이 있었는데 이렇게 하면 000에서 나는 냄새로 나쁜 병이 범접하지 못한다고 믿었다. ","wordType":1},{"x":3,"y":1,"direction":2,"word":"인슐린","info":"우리 몸의 혈당을 낮추는 유일한 호르몬으로 1형 당뇨병은 이 호르몬의 생산이 충분히 이루어지지 않아 생긴다.  ","wordType":8},{"x":1,"y":1,"direction":1,"word":"사미인곡","info":"조선 선조 때 송강 정철이 지은 가사로 임금에 대한 간절한 충정을 한 여인이 남편을 사모하는 마음에 비유하여 우의적으로 표현하였다. ","wordType":1},{"x":1,"y":0,"direction":2,"word":"공사","info":"넓은 의미로 모든 건설, 수리, 설비 등의 작업 ","wordType":2},{"x":0,"y":0,"direction":1,"word":"조공","info":"종속국이 종주국에게 사신(使臣)을 파견해 예물을 진상하던 행위로 이에 대한 답례로서 종주국은 하사품을 보냈다. ","wordType":7},{"x":5,"y":2,"direction":2,"word":"견리사의","info":"눈 앞에 이익을 보더라도 먼저 옳은 일인지 아닌지를 생각하라는 뜻의 사자성어 ","wordType":5},{"x":4,"y":5,"direction":1,"word":"창의력","info":"새로운 것을 생각해 낼 수 있는 능력 또는 힘 ","wordType":6},{"x":4,"y":5,"direction":2,"word":"창세기","info":"구약성서의 첫 권","wordType":1},{"x":4,"y":7,"direction":1,"word":"기회주의자","info":"일관된 입장을 지니지 못하고 그때그때의 상황에 따라 자신에게 이익이 되는 쪽으로 행동하는 사람","wordType":1},{"x":8,"y":4,"direction":2,"word":"순환출자","info":"같은 그룹에 속한 계열사들이 돌아가면서 서로 자본을 대면서 자본을 늘리는 것을 가리킨다.  ","wordType":10},{"x":8,"y":4,"direction":1,"word":"순결","info":"더러운 것이 섞이지 않고 깨끗함","wordType":2},{"x":9,"y":2,"direction":2,"word":"불가결","info":"없어서는 아니 됨","wordType":2},{"x":6,"y":7,"direction":2,"word":"주작","info":"없는 사실을 꾸며서 만듦","wordType":2},{"x":7,"y":2,"direction":1,"word":"홑이불","info":"한 겹으로 된 얇은 이불","wordType":2},{"x":8,"y":0,"direction":2,"word":"어른이","info":"어른과 어린이를 합친 말로 키덜트와 같은 의미","wordType":2},{"x":6,"y":0,"direction":1,"word":"신조어","info":"새로 생겨난 말","wordType":2},{"x":8,"y":6,"direction":1,"word":"출출","info":"액체가 많이 넘치는 모양을 나타내는 말","wordType":2}]}