{"mapSizeX":10,"mapSizeY":9,"wordDatas":[{"x":0,"y":0,"direction":1,"word":"정경유착","info":"정치와 경제가 부정적으로 연결되어 있는 경우로 기업가는 정치인에게 불법 정치 자금을 제공하고, 정치인은 기업가에게 불법 특혜를 베푸는 관계 ","wordType":9},{"x":0,"y":0,"direction":2,"word":"정형시","info":"일정한 규칙적인 운율에 맞추어 지은 시로 3장 6구 45자 내외라는 형식이 있는 '시조'가 대표적이다. ","wordType":1},{"x":0,"y":2,"direction":1,"word":"시국선언","info":"문제가 되고 있는 사회 현안을 바로잡기 위해 행하는 선언","wordType":4},{"x":3,"y":2,"direction":2,"word":"언행일치","info":"말과 행동이 일치한다는 뜻으로 이것을 지키지 않는 정치인이나 연예인들이 비난을 받기도 한다.","wordType":5},{"x":2,"y":5,"direction":1,"word":"벤치마킹","info":"경쟁 기업의 경영 방식을 분석해 자사의 제품을 업그레이드 시켜 경쟁력을 높이는 전략","wordType":10},{"x":5,"y":5,"direction":2,"word":"킹크랩","info":"대게의 일종으로 고가의 해산물에 속하며 순우리말로는 '왕게'라고 한다. ","wordType":1},{"x":2,"y":7,"direction":1,"word":"부비트랩","info":"건드리면 폭발하는 간단한 장치로 사람을 죽이기 위한 간단한 덫, 장치류를 부르는 말","wordType":3},{"x":2,"y":7,"direction":2,"word":"부모","info":"아버지와 어머니를 아울러 이르는 말","wordType":2},{"x":0,"y":8,"direction":1,"word":"미혼모","info":"결혼을 하지 않은 상태로 아이를 낳은 여자","wordType":2},{"x":0,"y":6,"direction":2,"word":"아노미","info":"사회 구성원의 행동을 규제하는 도덕적 기준이 없는 혼돈의 상태. 이때 사회 구성원은 자기 통제력을 잃고 '000 상태'가 된다.","wordType":4},{"x":5,"y":6,"direction":1,"word":"크리스퍼","info":"동식물 유전자의 손상된 DNA를 잘라내고 정상 DNA로 교체하는 유전자 편집 기술로 '유전자 가위'라고도 부른다.","wordType":1},{"x":8,"y":6,"direction":2,"word":"퍼센트","info":"어떤 양의 전체 양에 대해 100분의 몇이 되는가를 나타내는 단위로 '백분율'이라고도 한다. ","wordType":3},{"x":7,"y":8,"direction":1,"word":"노트북","info":"가지고 다니면서 사용할 수 있도록 작고 가볍게 만든 개인용 컴퓨터 ","wordType":3},{"x":7,"y":4,"direction":2,"word":"프랑스","info":"유럽 연합 소속 국가 중 가장 영토가 큰 국가로 수도는 '파리'이다.","wordType":2},{"x":7,"y":4,"direction":1,"word":"프림","info":"커피에 넣어 먹는 ‘크림(cream)’을 일컫는 말 ","wordType":3},{"x":8,"y":1,"direction":2,"word":"중경삼림","info":"두 개의 독특한 러브스토리를 담은 옴니버스 영화로 '사랑에 유효기간이 있다면 만년으로 하고싶다'는 명대사로 유명. 왕가위 연출/양조위, 금성무 출연  ","wordType":6},{"x":8,"y":1,"direction":1,"word":"중독","info":"한 가지 일만을 반복적으로 하는 행동과 그렇게 하도록 하는 충동 (예) 마약00, 도박00, 알코올00 ","wordType":2},{"x":9,"y":0,"direction":2,"word":"고독","info":"세상에 홀로 떨어져 있는 듯이 매우 외롭고 쓸쓸함","wordType":2},{"x":6,"y":2,"direction":1,"word":"잠망경","info":"내부에서 바깥을 정찰할 때 사용되는 반사용 망원경으로 보통 잠수함에서 많이 사용된다. ","wordType":8},{"x":6,"y":0,"direction":2,"word":"나비잠","info":"갓난아이가 반듯이 누워 팔을 머리 위로 벌리고 자는 잠으로 그 모습이 마치 나비가 날아가는 모습과 비슷해 000이라고 부른다. ","wordType":3},{"x":5,"y":0,"direction":1,"word":"찰나","info":"어떤 일이나 사물 현상이 나타나는 바로 그 때 (예) 00의 순간 ","wordType":2}]}